LICENSE
README.md
setup.cfg
setup.py
RankBoostClassifier/__init__.py
RankBoostClassifier/rankBoostClassifier.py
RankBoostClassifier.egg-info/PKG-INFO
RankBoostClassifier.egg-info/SOURCES.txt
RankBoostClassifier.egg-info/dependency_links.txt
RankBoostClassifier.egg-info/requires.txt
RankBoostClassifier.egg-info/top_level.txt
RankBoostClassifier/Utils/__init__.py
RankBoostClassifier/Utils/dropout.py
RankBoostClassifier/Utils/getDEgenes.py
RankBoostClassifier/Utils/preprocess.py
RankBoostClassifier/Utils/rankTransform.py