Metadata-Version: 2.1
Name: RankBoostClassifier
Version: 0.11
Summary: To add
Home-page: https://github.com/cellsemantics/boosted_rank_classifier
Author: Suchet Aggarwal, Asmit Kumar Singh, Namrata Bhattacharya, Debarka Sengupta
Author-email: suchet18105@iiitd.ac.in, asmit18025@iiitd.ac.in, namrata.bhattacharya@hdr.qut.edu.au, debarka@iiitd.ac.in
License: Apache License 2.0
License-File: LICENSE
